duckdataframe/__init__.py
duckdataframe/duckdf.py
duckdataframe-0.0.1rc1.dist-info/WHEEL
duckdataframe-0.0.1rc1.dist-info/METADATA
duckdataframe-0.0.1rc1.dist-info/RECORD
